{"hash":"23c77270113a5bf65d78c68cdf6b50d60221b0c6","data":{"category":{"slug":"mineral-roller-soeasy","category":"roller","model":"mineral","colour":"","page":0,"pages":1,"products":[{"url":"https://www.soeasyblinds.co.uk/roller-blinds/budget-roller-blinds/prime-mineral","title":"Prime Mineral","description":"Min width: 250mm max width: 2438mm min drop: 250mm max drop: 2438mm fabric joins: blinds with a width and drop greater than 1730mm may be joined. Dependant on the fabric patterns will be matched. Fabric composition: polyester tube: robust aluminium tube control: sidewinder control only guarantee: 12 months fittings: included buy made to measure prime mineral budget roller blinds from soeasy blinds.","price":8.75,"paththumb":"4551414205653834.webp","category":"roller","colour":"","model":"mineral","site":"SoEasy Blinds","categories":["mineral","roller","mineral-roller"],"affiliate":{"link":"","value":0}}]}},"context":{}}