{"hash":"a492300f2cefe9a03379bff320ece1f4c674f5e7","data":{"category":{"slug":"black-splash-kingston","category":"","model":"splash","colour":"black","page":0,"pages":1,"products":[{"slug":"roller-splash-noir-blind","url":"https://www.kingstonblindsdirect.co.uk/product/spalsh-noir-roller/","title":"Splash Noir Roller Blind","description":"This slightly textured, dim-out fabric will bring a splash of colour to an interior. Available in many colours and blackout options available in the bella range. Splash noir roller blind available from leading blinds supplier kingston blinds direct. Order a free sample and get an instant price online.","price":11,"paththumb":"903949659765099.webp","category":"roller","colour":"black","model":"splash","site":"Kingston blindsdirect","categories":["black","splash","roller","black-splash","black-roller","splash-roller"],"affiliate":{"link":"","value":0}},{"slug":"vertical-splash-noir-blind","url":"https://www.kingstonblindsdirect.co.uk/product/spalsh-noir-vertical/","title":"Splash Noir Vertical Blind","description":"This slightly textured, dim-out fabric will bring a splash of colour to an interior. Available in many colours and blackout options available in the bella range. Splash noir vertical blind available from leading blinds supplier kingston blinds direct. Order a free sample and get an instant price online.","price":17,"paththumb":"903949659765099.webp","category":"vertical","colour":"black","model":"splash","site":"Kingston blindsdirect","categories":["black","splash","vertical","black-splash","black-vertical","splash-vertical"],"affiliate":{"link":"","value":0}}]}},"context":{}}