{"hash":"9420b40dc373fa82a162322183dcbdbfc90b9b74","data":{"category":{"slug":"white-banbury-value","category":"","model":"banbury","colour":"white","page":0,"pages":1,"products":[{"url":"https://www.blindsbypost.co.uk/vertical-blinds/banbury-white","title":"Banbury White","description":"Banbury white made to measure vertical blind.","price":11.95,"paththumb":"1355050005657195.webp","category":"vertical","colour":"white","model":"banbury","site":"Blinds By Post","categories":["white","banbury","vertical","white-banbury","white-vertical","banbury-vertical"],"affiliate":{"link":"","value":0.67}},{"url":"https://www.blindsbypost.co.uk/roller-blinds/banbury-white","title":"Banbury White","description":"Banbury white made to measure roller blind.","price":15,"paththumb":"402367761285908.webp","category":"roller","colour":"white","model":"banbury","site":"Blinds By Post","categories":["white","banbury","roller","white-banbury","white-roller","banbury-roller"],"affiliate":{"link":"","value":0.67}},{"url":"https://www.swiftdirectblinds.co.uk/roman-blinds/banbury-canvas/","title":"Banbury Canvas Roman Blind","description":"With a chic and subtle style, the banbury canvas roman blind will suit a range of settings, whether classic or contemporary. This fabric blind has a sleek folding design that is compact and convenient at any window. The geometric pattern is highlighted in a soft cream tone and gives a touch of clean decoration in a versatile and neutral colour. Product id: db-rom1050 fabric colour: canvas material: 78% polyester 14% cotton 8% linen lining: light filtering poly/cotton blended lining headrail: durable white headrail with top or face fix brackets.","price":23.65,"paththumb":"2479847175147067.webp","category":"roman","colour":"white","model":"banbury","site":"Swift directblinds","categories":["white","banbury","roman","white-banbury","white-roman","banbury-roman"],"affiliate":{"link":"","value":0.52}},{"url":"https://www.swiftdirectblinds.co.uk/curtains/banbury-canvas/","title":"Banbury Canvas Curtain","description":"Subtle and stylish, this curtain is ideal for enhancing a neutral scheme. The banbury canvas curtain features a clean geometric pattern of overlapping lines creating a dimensional woven effect. This design will suit a contemporary scheme or a more classic setting and features a full lining that is sure to give an elegant, quality look to the fabric. Product id: db-cur1172 fabric colour: canvas material: 78% polyester 14% cotton 8% linen lining: light filtering poly/cotton blended lining energy saving rating: er2 - medium energy saving value - increase to er3 (high) by adding thermal lining light filtering: yes banbury canvas curtain in cream.","price":32.77,"paththumb":"5004889739405991.webp","category":"curtains-and","colour":"white","model":"banbury","site":"Swift directblinds","categories":["white","banbury","curtains-and","white-banbury","white-curtains-and","banbury-curtains-and"],"affiliate":{"link":"","value":0.52}}]}},"context":{}}