{"hash":"95f6c48e8e145a688d5a2c668ffedb333f6559ab","data":{"category":{"slug":"cream-vintage-curtains-and","category":"curtains-and","model":"vintage","colour":"cream","products":[{"url":"https://www.swiftdirectblinds.co.uk/curtains/butterfly-vintage/","title":"Butterfly Vintage Curtain","description":"Butterfly is a beautiful butterfly themed fabric with many elegant colours to choose from. Thesecream curtains are perfect to bring nature indoors and add a splash of colour at the same time. Product id: db-cur0976 fabric colour: vintage material: 100% cotton lining: light filtering poly/cotton blended lining energy saving rating: er2 - medium energy saving value - increase to er3 (high) by adding thermal lining light filtering: yes butterfly vintage curtain in cream/pink/multicoloured.","price":24.42,"paththumb":"3023153474833872.webp","category":"curtains-and","colour":"cream","model":"vintage","site":"Swift directblinds","categories":["cream","cream-vintage","cream-vintage-curtains-and","cream-curtains-and","vintage","vintage-curtains-and","curtains-and"]}]}},"context":{}}