{"hash":"38375b0e4b6e9bc1a9f89c06506289d511ccd694","data":{"category":{"slug":"pink-venetian-bbp","category":"venetian","model":"","colour":"pink","page":0,"pages":1,"products":[{"url":"https://www.blindsbypost.co.uk/venetian-blinds/metal-venetian-blinds/rosewood-woodline-9404","title":"Rosewood","description":"Rosewood woodline 9404 wood effect metal venetian blind.","price":15,"paththumb":"1938815743575984.webp","category":"venetian","colour":"pink","model":"","site":"Blinds By Post","categories":["pink","venetian","pink-venetian"],"affiliate":{"link":"","value":0}}]}},"context":{}}