{"hash":"ea96f9fde5addaf53a0aab9990458034f594460e","data":{"category":{"slug":"grey-nordic-roller","category":"roller","model":"nordic","colour":"grey","products":[{"url":"https://www.blindsbypost.co.uk/roller-blinds/crush-nordic-mist","title":"Crush Nordic Mist","description":"Crush nordic mist made to measure roller blind.","price":18,"paththumb":"5366445192018431.webp","category":"roller","colour":"grey","model":"nordic","site":"Blinds By Post","categories":["grey","grey-nordic","grey-nordic-roller","grey-roller","nordic","nordic-roller","roller"],"affiliate":{"link":"","value":0}}]}},"context":{}}