{"hash":"97001404ee504a74a4fbd79f24186c2197c01c3d","data":{"category":{"slug":"beige-rainbow-venetian-swift","category":"venetian","model":"rainbow","colour":"beige","page":0,"pages":1,"products":[{"url":"https://www.swiftdirectblinds.co.uk/venetian-blinds/rainbow-35-pale-mushroom-t0061-2/","title":"Rainbow 35mm Pale Mushroom Tr0061 Aluminium Venetian","description":"Their extensive range of gloss and matt finish venetian blinds, available in a full spectrum of colour. This dark cream venetian blind will look great in rooms with a warm colour scheme. Product id: db-trven0246 fabric colour: pale mushroom t0061 material: aluminium headrail: co-ordinating slimline aluminium headrail - face or top fix brackets slat width: 35mm slat material: aluminium control type: raise and lower cords / clearwand tilt energy saving rating: er1 - lowest energy saving value - due to blind type or fabric light filtering: yes rainbow 35mm pale mushroom tr0061 aluminium venetian in cream.","price":12.85,"paththumb":"4230239046971243.webp","category":"venetian","colour":"beige","model":"rainbow","site":"Swift directblinds","categories":["beige","rainbow","venetian","beige-rainbow","beige-venetian","rainbow-venetian"],"affiliate":{"link":"","value":0.52}},{"url":"https://www.swiftdirectblinds.co.uk/venetian-blinds/rainbow-50-pale-mushroom-t0061-2/","title":"Rainbow 50mm Pale Mushroom Tr0061 Aluminium Venetian","description":"Their extensive range of gloss and matt finish venetian blinds, available in a full spectrum of colour. This dark cream venetian blind will look great in rooms with a warm colour scheme. Product id: db-trven0151 fabric colour: pale mushroom t0061 material: aluminium headrail: co-ordinating slimline aluminium headrail - face or top fix brackets slat width: 50mm slat material: aluminium control type: raise and lower cords / clearwand tilt energy saving rating: er1 - lowest energy saving value - due to blind type or fabric light filtering: yes rainbow 50mm pale mushroom tr0061 aluminium venetian in brown.","price":12.85,"paththumb":"5428573419600317.webp","category":"venetian","colour":"beige","model":"rainbow","site":"Swift directblinds","categories":["beige","rainbow","venetian","beige-rainbow","beige-venetian","rainbow-venetian"],"affiliate":{"link":"","value":0.52}}]}},"context":{}}