{"hash":"739799a4aff2cc4084b49d3d34899c96a854d468","data":{"category":{"slug":"purple-rainbow-value","category":"","model":"rainbow","colour":"purple","page":0,"pages":1,"products":[{"url":"https://www.swiftdirectblinds.co.uk/venetian-blinds/rainbow-25-shelby-dc025/","title":"Turin 25mm Lavender Purple Aluminium Venetian","description":"Their extensive range of gloss and matt finishes in a full spectrum of colour means we are sure you will find something for you. This vibrant purplevenetian blind is perfect to brighten up any room in your home with a splash of colour. Product id: db-dven0363 fabric colour: lavender purple s25025 material: aluminium headrail: co-ordinating slimline aluminium headrail - face or top fix brackets slat width: 25mm slat material: aluminium control type: cord & wand energy saving rating: er1 - lowest energy saving value - due to blind type or fabric light filtering: yes turin 25mm lavender purple aluminium venetian in purple.","price":8.75,"paththumb":"1584743734883269.webp","category":"venetian","colour":"purple","model":"rainbow","site":"Swift directblinds","categories":["purple","rainbow","venetian","purple-rainbow","purple-venetian","rainbow-venetian"],"affiliate":{"link":"","value":0}},{"url":"https://www.swiftdirectblinds.co.uk/perfect-fit-venetian-blinds/rainbow-25-shelby-dc025/","title":"Turin 25mm Lavender Purple Perfect Fit Venetian Blind","description":"Their extensive range of gloss and matt finishes in a full spectrum of colour means we are sure you will find something for you. This vibrant purplevenetian blind is perfect to brighten up any room in your home with a splash of colour. Product id: db-dpfven0363 fabric colour: lavender purple s25025 material: aluminium headrail: minimal perfect fit framework - easy drill-free installation clip slat width: 25mm control type: tilt wand, tensioned cord-free raise.","price":17.5,"paththumb":"4993463122016190.webp","category":"perfect-fit","colour":"purple","model":"rainbow","site":"Swift directblinds","categories":["purple","rainbow","perfect-fit","purple-rainbow","purple-perfect-fit","rainbow-perfect-fit"],"affiliate":{"link":"","value":0}}]}},"context":{}}