{"hash":"9420b40dc373fa82a162322183dcbdbfc90b9b74","data":{"category":{"slug":"grey-vesper-swift","category":"","model":"vesper","colour":"grey","page":0,"pages":1,"products":[{"url":"https://www.swiftdirectblinds.co.uk/roller-blinds/vesper-lunar-grey/","title":"Vesper Lunar Grey Roller Blind","description":"Their semi-translucent vesper range, meshes stylish striped opaque and see-though stripes, with colour favourites to create a truly stunning finish. Vesper vesper grey roller blinds are modern and stylish, and the light streaming through the voile stripes makes for a beautiful effect. Coming with clean white compontents and quality checked before leaving their warehouse, their roller blinds are a family favourite for their durability, value for money and clean finishes.","price":15.13,"paththumb":"7892693088214977.webp","category":"roller","colour":"grey","model":"vesper","site":"Swift directblinds","categories":["grey","vesper","roller","grey-vesper","grey-roller","vesper-roller"],"affiliate":{"link":"","value":0.52}}]}},"context":{}}