{"hash":"4022c33e90e139f487400db2c65282d3a5c729bd","data":{"category":{"slug":"white-dimout-perfect-fit","category":"perfect-fit","model":"dimout","colour":"white","products":[{"url":"https://www.makemyblinds.co.uk/snow-white-honeycomb-dimout-perfect-fit.html","title":"Snow White Honeycomb Dimout Perfect Fit","metadescription":"Snow white honeycomb dimout perfect fit","productdescription":"The gorgeous pleated snow white honeycomb dimout perfect fit blind is simple, stylish and versatile. Its elegant white can be paired in an endless amount of ways, to add a modern, classy feel to its paired window. You simply cant go wrong with a clean, crisp white blind struggling to cover your french doors? Pleated perfect fit blinds are a great way to shade each pane, and provide style and privacy at the same time. The blackout pleated fabric will gently filter the light coming into your room, while still giving you peaceful seclusion looking for a solution for your conservatory windows? Perfect fits are designed to clip on quickly and easily - with no screws, drilling or tools required all of their blinds are sold with built-in child safety mechanisms. We adhere to the guidelines set out by the british blind and shutter association and take safety extremely seriously. All blinds come with the relevant child safety instructions and warnings. Please ensure you follow the provided instructions and warnings carefully. Please visit www.Makeitsafe.Org.Uk to find out more.","price":19.99,"paththumb":"169182559633338.webp","category":"perfect-fit","colour":"white","model":"dimout","site":"Make My Blinds","categories":["white","white-dimout","white-dimout-perfect-fit","white-perfect-fit","dimout","dimout-perfect-fit","perfect-fit"]}]}},"context":{}}