{"hash":"1f2c93b133f98e54a82454b599360df02fc0c55a","data":{"category":{"slug":"blue-scandi-swift","category":"","model":"scandi","colour":"blue","page":0,"pages":1,"products":[{"slug":"roman-scandi-birds-aqua-blind-b","url":"https://www.swiftdirectblinds.co.uk/roman-blinds/scandi-birds-aqua/","title":"Scandi Birds Aqua Roman Blind","description":"One of the most popular colourways from the iliv scandi collection. This bold print is suitable for both traditional and modern homes and is trending in its style. Add a focal point to your windows with this roman blind, handmade in their own west yorkshire factory. Swift direct blinds are proud that their customers voted their roman blinds excellent on trustpilot reviews. Product id: db-rom0902 fabric colour: aqua material: 100% cotton lining: light filtering poly/cotton blended lining headrail: durable white headrail with top or face fix brackets.","price":17.59,"paththumb":"1063047023139441.webp","category":"roman","colour":"blue","model":"scandi","site":"Swift directblinds","categories":["blue","scandi","roman","blue-scandi","blue-roman","scandi-roman"],"affiliate":{"link":"","value":0.52}},{"slug":"curtains-and-scandi-birds-aqua-curtain","url":"https://www.swiftdirectblinds.co.uk/curtains/scandi-birds-aqua/","title":"Scandi Birds Aqua Curtain","description":"Their scandinavian-inspired scandi birds come in bright on-trend shades. Perfect for adding to a kitchen to brighten the scheme or bringing nature to your modern home. Product id: db-cur1036 fabric colour: aqua material: 100% cotton lining: light filtering poly/cotton blended lining energy saving rating: er2 - medium energy saving value - increase to er3 (high) by adding thermal lining light filtering: yes scandi birds aqua curtain in blue.","price":24.42,"paththumb":"4509200770824209.webp","category":"curtains-and","colour":"blue","model":"scandi","site":"Swift directblinds","categories":["blue","scandi","curtains-and","blue-scandi","blue-curtains-and","scandi-curtains-and"],"affiliate":{"link":"","value":0.52}}]}},"context":{}}