{"hash":"4022c33e90e139f487400db2c65282d3a5c729bd","data":{"category":{"slug":"purple-premium","category":"","model":"premium","colour":"purple","products":[{"url":"https://www.blinds-2go.co.uk/venetian-blinds/15852/premium-romantic-purple.html","title":"Premium Romantic Purple Venetian Blind - 25mm Slat","metadescription":"This rich and deep purple tone with gloss finish is an absolute gem; it brings both colour and a sense of reserved flamboyance to the party. \r\n\r\nFrom plum to damson and blackcurrant this blind will look lovely with other purple tones; on the other hand it will lift a scheme of mo","productdescription":"This rich and deep purple tone with gloss finish is an absolute gem; it brings both colour and a sense of reserved flamboyance to the party. \r\n\r\nFrom plum to damson and blackcurrant this blind will look lovely with other purple tones; on the other hand it will lift a scheme of mo","price":14.52,"paththumb":"1919652941142160.webp","category":"venetian","colour":"purple","model":"premium","site":"blinds2go","categories":["purple","purple-premium","purple-premium-venetian","purple-venetian","premium","premium-venetian","venetian"]}]}},"context":{}}