{"hash":"668757039dc4b448cdd97d1a9ab9286fa9c29a2b","data":{"category":{"slug":"cream-vitra-roller","category":"roller","model":"vitra","colour":"cream","page":0,"pages":1,"products":[{"url":"https://www.kingstonblindsdirect.co.uk/product/vitra-cream-roller/","title":"Vitra Cream Roller Blind","description":"A blackout fabric which provides a block of colour. Available in other colours. The vitra cream roller blind is a patterned cream blind. We offer free delivery for all orders over 145. Get a free sample. Nationwide coverage.","price":13,"paththumb":"6051816644999487.webp","category":"roller","colour":"cream","model":"vitra","site":"Kingston blindsdirect","categories":["cream","vitra","roller","cream-vitra","cream-roller","vitra-roller"],"affiliate":{"link":"","value":0}},{"url":"https://www.kingstonblindsdirect.co.uk/product/vitra-marlin-roller/","title":"Vitra Marlin Roller Blind","description":"A blackout fabric which provides a block of colour. Available in other colours. The vitra marlin roller blind comes in grey. With nationwide coverage, we have free delivery on orders over 145. Get a free sample.","price":13,"paththumb":"3235754422192415.webp","category":"roller","colour":"cream","model":"vitra","site":"Kingston blindsdirect","categories":["cream","vitra","roller","cream-vitra","cream-roller","vitra-roller"],"affiliate":{"link":"","value":0}}]}},"context":{}}