{"hash":"6f4cba850bd6fbbc69e9897ff8ea33d1bb5aa2f5","data":{"category":{"slug":"grey-aria-vertical-value","category":"vertical","model":"aria","colour":"grey","page":0,"pages":1,"products":[{"url":"https://www.blindsbypost.co.uk/vertical-blinds/aria-zinc","title":"Aria Zinc","description":"Aria zinc made to measure vertical blind.","price":11.95,"paththumb":"7511542186879307.webp","category":"vertical","colour":"grey","model":"aria","site":"Blinds By Post","categories":["grey","aria","vertical","grey-aria","grey-vertical","aria-vertical"],"affiliate":{"link":"","value":0}},{"url":"https://www.swiftdirectblinds.co.uk/vertical-blinds/aria-stone/","title":"Aria Stone 89mm Vertical Blind","description":"Their aria range comes in many different colours and has a perfect pattern which gives it more a sophisticated look to any room they are fitted in. The stylish pattern of this creamvertical blind will fit perfectly into any room in your home. Product id: sdb-vtb0923 fabric colour: stone material: 100% polyester headrail: white slimline headrail supported by white steel brackets - top or face fixable slat width: 89mm control type: smooth chain operation with cord tilt or wand tilt and pull energy saving rating: er2 - medium energy saving value - effective thermal retention light filtering: yes aria stone 89mm vertical blind in cream/brown.","price":14.14,"paththumb":"1320660868908743.webp","category":"vertical","colour":"grey","model":"aria","site":"Swift directblinds","categories":["grey","aria","vertical","grey-aria","grey-vertical","aria-vertical"],"affiliate":{"link":"","value":0}}]}},"context":{}}