{"hash":"38375b0e4b6e9bc1a9f89c06506289d511ccd694","data":{"category":{"slug":"chenille-roller-bbp","category":"roller","model":"chenille","colour":"","page":0,"pages":1,"products":[{"url":"https://www.blindsbypost.co.uk/roller-blinds/chenille-angora","title":"Chenille Angora","description":"Chenille angora made to measure roller blind.","price":18,"paththumb":"7651281839256269.webp","category":"roller","colour":"","model":"chenille","site":"Blinds By Post","categories":["chenille","roller","chenille-roller"],"affiliate":{"link":"","value":0}},{"url":"https://www.blindsbypost.co.uk/roller-blinds/chenille-silver","title":"Chenille Silver","description":"Chenille silver made to measure roller blind.","price":18,"paththumb":"4890877116307550.webp","category":"roller","colour":"grey","model":"chenille","site":"Blinds By Post","categories":["grey","chenille","roller","grey-chenille","grey-roller","chenille-roller"],"affiliate":{"link":"","value":0}},{"url":"https://www.blindsbypost.co.uk/roller-blinds/chenille-mink","title":"Chenille Mink","description":"Chenille mink made to measure roller blind.","price":18,"paththumb":"196995545788944.webp","category":"roller","colour":"","model":"chenille","site":"Blinds By Post","categories":["chenille","roller","chenille-roller"],"affiliate":{"link":"","value":0}},{"url":"https://www.blindsbypost.co.uk/roller-blinds/chenille-mauve","title":"Chenille Mauve","description":"Chenille mauve made to measure roller blind.","price":18,"paththumb":"3713934699804793.webp","category":"roller","colour":"","model":"chenille","site":"Blinds By Post","categories":["chenille","roller","chenille-roller"],"affiliate":{"link":"","value":0}}]}},"context":{}}