{"hash":"1f2c93b133f98e54a82454b599360df02fc0c55a","data":{"category":{"slug":"red-meadow-roof-swift","category":"roof","model":"meadow","colour":"red","page":0,"pages":1,"products":[{"slug":"roof-meadow-flower-solar-redcurrant-pleated-skylight-blind","url":"https://www.swiftdirectblinds.co.uk/pleated-skylight-blinds/meadow-flower-solar-redcurrant/","title":"Meadow Flower Solar Redcurrant Pleated Skylight Blind","description":"Meadow flower solar has a beautiful patterned fabric which really stand out, there are also different variations of fun colours. The flowers really make your home feel warm and comfortable. Featuring an aluminium coated back, this fabric reflects heat in summer and retains heat in summer. A perfect thermal fabric. Product id: db-pls0124 fabric colour: redcurrant material: 100% polyester headrail: white rails and hardware with pull down tab and visible guide wires to support the blind fabric.","price":40.94,"paththumb":"6263321246983101.webp","category":"roof","colour":"red","model":"meadow","site":"Swift directblinds","categories":["red","meadow","roof","red-meadow","red-roof","meadow-roof"],"affiliate":{"link":"","value":0.52}}]}},"context":{}}