{"hash":"38375b0e4b6e9bc1a9f89c06506289d511ccd694","data":{"category":{"slug":"cream-missprint","category":"","model":"missprint","colour":"cream","page":0,"pages":1,"products":[{"url":"https://www.blindsbypost.co.uk/roller-blinds/missprint-blackout-little-trees-egg-shell","title":"Missprint Blackout Little Trees Egg Shell","description":"Roller blinds made to measure blackout roller blind missprint blackout little trees egg shell made to measure roller blind.","price":27.5,"paththumb":"8472980692405692.webp","category":"roller","colour":"cream","model":"missprint","site":"Blinds By Post","categories":["cream","missprint","roller","cream-missprint","cream-roller","missprint-roller"],"affiliate":{"link":"","value":0}}]}},"context":{}}