{"hash":"7fd82894ef4cd4e7cd7997eb713913b906fe029b","data":{"category":{"slug":"brown-flying","category":"","model":"flying","colour":"brown","products":[{"url":"https://www.247blinds.co.uk/flying-pleated-1264-shiny-cappuccino-velux-loft-blind","title":"Flying Pleated, 1264 Shiny Cappuccino - Velux Loft Blind","description":"Softens the incoming light. Offers both privacy and good looks. Opaqueinstall in minutes with the velux pick & click system. Not fixed to bottom or top - allowing 100% flexibility. Flying pleated, 1264 shiny cappuccino - velux loft blind softens the incoming light.","price":55.9,"paththumb":"4177204371537952.webp","category":"roof","colour":"brown","model":"flying","site":"247blinds","categories":["brown","brown-flying","brown-flying-roof","brown-roof","flying","flying-roof","roof"],"affiliate":{"link":"","value":0}},{"url":"https://www.247blinds.co.uk/flying-pleated-1260-misty-brown-velux-loft-blind","title":"Flying Pleated, 1260 Misty Brown - Velux Loft Blind","description":"Softens the incoming light. Offers both privacy and good looks. Transparentinstall in minutes with the velux pick & click system. Not fixed to bottom or top - allowing 100% flexibility. Flying pleated, 1260 misty brown - velux loft blind softens the incoming light.","price":55.9,"paththumb":"6047294981695993.webp","category":"roof","colour":"brown","model":"flying","site":"247blinds","categories":["brown","brown-flying","brown-flying-roof","brown-roof","flying","flying-roof","roof"],"affiliate":{"link":"","value":0}}]}},"context":{}}