{"hash":"9420b40dc373fa82a162322183dcbdbfc90b9b74","data":{"category":{"slug":"mineral-vertical-bbp","category":"vertical","model":"mineral","colour":"","page":0,"pages":1,"products":[{"url":"https://www.blindsbypost.co.uk/vertical-blinds/monroe-mineral","title":"Monroe Mineral","description":"Monroe mineral made to measure vertical blind.","price":12.5,"paththumb":"660881090083310.webp","category":"vertical","colour":"","model":"mineral","site":"Blinds By Post","categories":["mineral","vertical","mineral-vertical"],"affiliate":{"link":"","value":0.67}},{"url":"https://www.blindsbypost.co.uk/vertical-blinds/shot-silk-mineral","title":"Shot Silk Mineral","description":"Shot silk mineral made to measure vertical blind.","price":13.45,"paththumb":"7567784277208262.webp","category":"vertical","colour":"","model":"mineral","site":"Blinds By Post","categories":["mineral","vertical","mineral-vertical"],"affiliate":{"link":"","value":0.67}}]}},"context":{}}