{"hash":"cc93fe7a95f2c251b5f0707da2b51d25e7cc40ed","data":{"category":{"slug":"cream-corsica-roller","category":"roller","model":"corsica","colour":"cream","products":[{"url":"https://www.soeasyblinds.co.uk/roller-blinds/standard-roller-blinds/corsica-ivory","title":"Corsica Ivory","description":"Min width: 200mm max width: 1940mm min drop: 300mm max drop: 3000mm fabric composition: polyester tube: robust aluminium tube control: sidewinder or spring control guarantee: 12 months fittings: included buy made to measure corsica ivory standard roller blinds from soeasy blinds. Order quality standard roller blinds online today at low prices with fast uk delivery.","price":29.51,"paththumb":"1361810606327446.webp","category":"roller","colour":"cream","model":"corsica","site":"SoEasy Blinds","categories":["cream","cream-corsica","cream-corsica-roller","cream-roller","corsica","corsica-roller","roller"]},{"url":"https://www.soeasyblinds.co.uk/perfect-fit-blinds/perfect-fit-roller-blinds/corsica-ivory-3","title":"Corsica Ivory","description":"Min width: 350mm max width: 1400mm min drop: 150mm max drop: 1100mm fabric composition: polyester guarantee: 12 months controls: tensioned system, move bottom bar to raise/lower blind. Buy made to measure corsica ivory perfect fit roller blinds from soeasy blinds. Order quality perfect fit roller blinds online today at low prices with fast uk delivery.","price":66.01,"paththumb":"1955957954726112.webp","category":"roller","colour":"cream","model":"corsica","site":"SoEasy Blinds","categories":["cream","cream-corsica","cream-corsica-roller","cream-roller","corsica","corsica-roller","roller"]}]}},"context":{}}