{"hash":"cc9898521d78078de70102c743bb1bb7b36fd4c5","data":{"category":{"slug":"yellow-stains","category":"","model":"stains","colour":"yellow","products":[{"url":"https://www.soeasyblinds.co.uk/venetian-blinds/wooden-venetian-blinds/stains-golden-oak","title":"Stains Golden Oak","metadescription":"Buy made to measure Stains Golden Oak Wooden Venetian Blinds from SoEasy Blinds. Order quality Wooden Venetian Blinds online today at low prices with fast UK delivery","productdescription":"Min Width: 305mm Max Width: 2896mm\r\n \tMin Drop: 305mm Max Drop: 3500mm\r\n \tSlat Composition: Basswood\r\n \tSlat Widths Available: 25mm, 35mm &amp;amp; 50mm\r\n \tGuarantee: 12 Months\r\nControls: A choice of Standard Controls (left hand tilt / right hand raise &amp;amp; lower), Left Hand Controls (left hand tilt / left hand raise &amp;amp; lower) or Right Hand Controls (right hand tilt / right hand raise &amp;amp; lower).\r\n \tStyling: Co-ordinating cords as standard, tapes optional. Stained slat ends\r\n \tPelmet: Co-ordinating pelmet\r\n \tHeadrail: Robust aluminium headrail, 37mm wide x 38mm deep (25 &amp;amp; 35mm slats) 51mm wide x 57mm deep (50mm slats)","price":79.11,"paththumb":"7934504824969105.webp","category":"venetian","colour":"yellow","model":"stains","site":"SoEasy Blinds","categories":["yellow","yellow-stains","yellow-stains-venetian","yellow-venetian","stains","stains-venetian","venetian"]}]}},"context":{}}