{"hash":"3d043a710fa95b489715af3335b08d5f868b2ccc","data":{"category":{"slug":"grey-moonstone-roller-b2go","category":"roller","model":"moonstone","colour":"grey","page":0,"pages":1,"products":[{"url":"https://www.blinds-2go.co.uk/roller-blinds/31889/choices-apollo-moonstone.html","title":"Choices Apollo Moonstone Roller Blind","description":"This classic looking choices apollo moonstone roller blind brings a touch of timeless beauty to your home. Elegant texture covers a natural and neutral coloured fabric to create a chic, luxurious look. The colourway will complement so many schemes, from light to dark, creating this classic looking choices apollo moonstone roller blind brings a touch of timeless beauty to your home.","price":19.28,"paththumb":"29920432087450.webp","category":"roller","colour":"grey","model":"moonstone","site":"blinds2go","categories":["grey","moonstone","roller","grey-moonstone","grey-roller","moonstone-roller"],"affiliate":{"link":"","value":0}}]}},"context":{}}