{"hash":"805f98a11224a1d1339ef434f05aedb94e86b99c","data":{"category":{"slug":"cream-prime-perfect-fit","category":"perfect-fit","model":"prime","colour":"cream","page":0,"pages":1,"products":[{"url":"https://www.swiftdirectblinds.co.uk/perfect-fit-venetian-blinds/verona-prime-25mm-magnolia/","title":"Verona Prime 25mm Magnolia Perfect Fit Venetian Blind","description":"Their range of verona 25mm perfect fit aluminium venetian blinds blend simplicity with functionality, and are perfect for the office - home or away. A neutral cream tone, this magnolia perfect fit venetian blind adds a stylish cream shade to your home. Match with other neutral tones for a modern style, or mix with wood accessories for a chic finished look. Perfect fit blinds are designed for use with a upvc door and window as they are drill, and screw-free.","price":15.76,"paththumb":"7504951186926588.webp","category":"perfect-fit","colour":"cream","model":"prime","site":"Swift directblinds","categories":["cream","cream-prime","cream-prime-perfect-fit","cream-perfect-fit","prime","prime-perfect-fit","perfect-fit"],"affiliate":{"link":"","value":0}}]}},"context":{}}