{"hash":"9420b40dc373fa82a162322183dcbdbfc90b9b74","data":{"category":{"slug":"white-windsor-roman-swift","category":"roman","model":"windsor","colour":"white","page":0,"pages":1,"products":[{"url":"https://www.swiftdirectblinds.co.uk/roman-blinds/windsor-canvas/","title":"Windsor Canvas Roman Blind","description":"Made from silky-feel, neutral toned fabric and beautifully enriched with strands of metallic yarn, this window blind will make a simple yet sophisticated update for your decor. The windsor canvas roman blind features a lustrous and sparkling finish that is given further richness by the visual effect of the smooth curving pattern. Product id: db-rom1073 fabric colour: canvas material: 41% cotton 36% polyester 23% viscose lining: light filtering poly/cotton blended lining headrail: durable white headrail with top or face fix brackets.","price":26.4,"paththumb":"1546041479244021.webp","category":"roman","colour":"white","model":"windsor","site":"Swift directblinds","categories":["white","windsor","roman","white-windsor","white-roman","windsor-roman"],"affiliate":{"link":"","value":0.52}}]}},"context":{}}